{
  "project_info": {
    "project_number": "635179563280",
    "project_id": "telegramcontest-e7d20",
    "storage_bucket": "telegramcontest-e7d20.firebasestorage.app"
  },
  "client": [
    {
      "client_info": {
        "mobilesdk_app_id": "1:635179563280:android:0ba5ee14b5a02395f90d95",
        "android_client_info": {
          "package_name": "org.telegram.messenger"
        }
      },
      "oauth_client": [],
      "api_key": [
        {
          "current_key": "AIzaSyB46tzRgY4UI6AjPWgqyZRSS3sdMVt025c"
        }
      ],
      "services": {
        "appinvite_service": {
          "other_platform_oauth_client": []
        }
      }
    },
    {
      "client_info": {
        "mobilesdk_app_id": "1:635179563280:android:a48b6acb45d2adabf90d95",
        "android_client_info": {
          "package_name": "org.telegram.messenger.beta"
        }
      },
      "oauth_client": [],
      "api_key": [
        {
          "current_key": "AIzaSyB46tzRgY4UI6AjPWgqyZRSS3sdMVt025c"
        }
      ],
      "services": {
        "appinvite_service": {
          "other_platform_oauth_client": []
        }
      }
    }
  ],
  "configuration_version": "1"
}